siamese/__init__.py
siamese/_reports.py
siamese/_stats.py
siamese/distributions.py
siamese/failures.py
siamese/status.py
siamese/models/base.py
siamese/models/buffer.py
siamese/models/line.py
siamese/models/machine.py
siamese/models/source.py
siamese_optimizer-0.0.2.dist-info/LICENSE
siamese_optimizer-0.0.2.dist-info/METADATA
siamese_optimizer-0.0.2.dist-info/WHEEL
siamese_optimizer-0.0.2.dist-info/top_level.txt
siamese_optimizer-0.0.2.dist-info/RECORD
