Metadata-Version: 2.1
Name: siamese-optimizer
Version: 0.0.2
Summary: A Python package for manufacturing and assembly lines simulation and optimization.
Home-page: https://github.com/GusFurtado/siamese-optimizer
Download-URL: https://github.com/GusFurtado/siamese-optimizer/archive/0.0.2.tar.gz
Author: Gustavo Furtado
Author-email: gustavofurtado2@gmail.com
License: MIT
Keywords: python,simulation,networkx,manufacturing,industry,simpy,assembly-line,production-line,line-engineering,manufacturing-line
Classifier: Development Status :: 3 - Alpha
Classifier: Intended Audience :: Manufacturing
Classifier: Intended Audience :: Science/Research
Classifier: Topic :: Scientific/Engineering
Classifier: License :: OSI Approved :: MIT License
Classifier: Natural Language :: English
Classifier: Natural Language :: Portuguese (Brazilian)
Classifier: Programming Language :: Python :: 3
Classifier: Programming Language :: Python :: 3.6
License-File: LICENSE
Requires-Dist: networkx
Requires-Dist: numpy
Requires-Dist: plotly
Requires-Dist: simpy
